{
    "type": "object",
    "properties": {
        "MaxRecords": {
            "required": false,
            "type": "string"
        },
        "Marker": {
            "required": false,
            "type": "string"
        },
        "requestBody": {
            "description": "Parameter input for DescribeDBInstanceAutomatedBackups. ",
            "properties": {
                "DBInstanceIdentifier": {
                    "description": "(Optional) The user-supplied instance identifier. If this parameter is specified, it must match the identifier of an existing DB instance. It returns information from the specific DB instance' automated backup. This parameter isn't case-sensitive. ",
                    "type": "string"
                },
                "DbiResourceId": {
                    "description": "The resource ID of the DB instance that is the source of the automated backup. This parameter isn't case-sensitive. ",
                    "type": "string"
                },
                "Filters": {
                    "description": "<p>A filter that specifies which resources to return based on status.</p> <p>Supported filters are the following:</p> <ul> <li> <p> <code>status</code> </p> <ul> <li> <p> <code>active</code> - automated backups for current instances</p> </li> <li> <p> <code>retained</code> - automated backups for deleted instances</p> </li> <li> <p> <code>creating</code> - automated backups that are waiting for the first automated snapshot to be available</p> </li> </ul> </li> <li> <p> <code>db-instance-id</code> - Accepts DB instance identifiers and Amazon Resource Names (ARNs) for DB instances. The results list includes only information about the DB instance automated backupss identified by these ARNs.</p> </li> <li> <p> <code>dbi-resource-id</code> - Accepts DB instance resource identifiers and DB Amazon Resource Names (ARNs) for DB instances. The results list includes only information about the DB instance resources identified by these ARNs.</p> </li> </ul> <p>Returns all resources by default. The status for each resource is specified in the response.</p>",
                    "items": {
                        "description": "<p>A filter name and value pair that is used to return a more specific list of results from a describe operation. Filters can be used to match a set of resources by specific criteria, such as IDs. The filters supported by a describe operation are documented with the describe operation.</p> <note> <p>Currently, wildcards are not supported in filters.</p> </note> <p>The following actions can be filtered:</p> <ul> <li> <p> <a>DescribeDBClusterBacktracks</a> </p> </li> <li> <p> <a>DescribeDBClusterEndpoints</a> </p> </li> <li> <p> <a>DescribeDBClusters</a> </p> </li> <li> <p> <a>DescribeDBInstances</a> </p> </li> <li> <p> <a>DescribePendingMaintenanceActions</a> </p> </li> </ul>",
                        "properties": {
                            "Name": {
                                "description": "The name of the filter. Filter names are case-sensitive.",
                                "type": "string"
                            },
                            "Values": {
                                "description": "One or more filter values. Filter values are case-sensitive.",
                                "items": {
                                    "type": "string"
                                },
                                "type": "array"
                            }
                        },
                        "required": [
                            "Name",
                            "Values"
                        ],
                        "type": "object"
                    },
                    "type": "array"
                },
                "Marker": {
                    "description": "The pagination token provided in the previous request. If this parameter is specified the response includes only records beyond the marker, up to <code>MaxRecords</code>.",
                    "type": "string"
                },
                "MaxRecords": {
                    "description": "The maximum number of records to include in the response. If more records exist than the specified <code>MaxRecords</code> value, a pagination token called a marker is included in the response so that the remaining results can be retrieved.",
                    "type": "integer"
                }
            },
            "type": "object"
        },
        "X_Amz_Content_Sha256": {
            "required": false,
            "type": "string"
        },
        "X_Amz_Date": {
            "required": false,
            "type": "string"
        },
        "X_Amz_Algorithm": {
            "required": false,
            "type": "string"
        },
        "X_Amz_Credential": {
            "required": false,
            "type": "string"
        },
        "X_Amz_Security_Token": {
            "required": false,
            "type": "string"
        },
        "X_Amz_Signature": {
            "required": false,
            "type": "string"
        },
        "X_Amz_SignedHeaders": {
            "required": false,
            "type": "string"
        }
    }
}